{
    "key": "group_63f64c160b480",
    "title": "Hazard Metadata",
    "fields": [
        {
            "key": "field_63f64c1e4780b",
            "label": "Image",
            "name": "hazard_image",
            "aria-label": "",
            "type": "image",
            "instructions": "<b>Image requirements:<\/b>\r\n<p>Images must be square and be at least 150px by 150px.<\/p>\r\n<p>Must be in PNG format and be optimized for web.<\/p>\r\n<p>Foreground must be white; background must be transparent.<\/p>\r\n<p>There must be padding built into the image. Because the icons are always displayed\r\ninside a circle, the padding is important to ensure the icon appears centred and leaves enough room around the edges of the circle.<\/p>\r\n<p>The preview above shows how the icon and background circle will appear on the site. Ensure the icon looks correct in this preview before saving your changes.<\/p>",
            "required": 0,
            "conditional_logic": 0,
            "wrapper": {
                "width": "",
                "class": "hazard-image-preview",
                "id": ""
            },
            "return_format": "array",
            "library": "all",
            "min_width": 150,
            "min_height": 150,
            "min_size": "",
            "max_width": "",
            "max_height": "",
            "max_size": "",
            "mime_types": "png",
            "preview_size": "thumbnail"
        },
        {
            "key": "field_641c9f8e4115a",
            "label": "Colour",
            "name": "colour",
            "aria-label": "",
            "type": "color_picker",
            "instructions": "",
            "required": 0,
            "conditional_logic": 0,
            "wrapper": {
                "width": "",
                "class": "",
                "id": ""
            },
            "default_value": "",
            "enable_opacity": 0,
            "return_format": "string"
        },
        {
            "key": "field_64512f7926090",
            "label": "Secondary Colour",
            "name": "secondary_colour",
            "aria-label": "",
            "type": "color_picker",
            "instructions": "",
            "required": 0,
            "conditional_logic": 0,
            "wrapper": {
                "width": "",
                "class": "",
                "id": ""
            },
            "default_value": "",
            "enable_opacity": 0,
            "return_format": "string"
        },
        {
            "key": "field_6670a630bc960",
            "label": "Has striped border",
            "name": "has_striped_border",
            "aria-label": "",
            "type": "true_false",
            "instructions": "",
            "required": 0,
            "conditional_logic": 0,
            "wrapper": {
                "width": "",
                "class": "",
                "id": ""
            },
            "message": "",
            "default_value": 0,
            "ui": 0,
            "ui_on_text": "",
            "ui_off_text": ""
        }
    ],
    "location": [
        [
            {
                "param": "taxonomy",
                "operator": "==",
                "value": "hazard_type"
            }
        ]
    ],
    "menu_order": 0,
    "position": "normal",
    "style": "default",
    "label_placement": "top",
    "instruction_placement": "label",
    "hide_on_screen": "",
    "active": true,
    "description": "",
    "show_in_rest": 1,
    "modified": 1725575592
}
